autodistill_yoloe/__init__.py
autodistill_yoloe/model.py
autodistill_yoloe-0.1.1.dist-info/METADATA
autodistill_yoloe-0.1.1.dist-info/WHEEL
autodistill_yoloe-0.1.1.dist-info/RECORD
