Metadata-Version: 2.4
Name: autodistill-yoloe
Version: 0.1.1
Summary: use YOLOE to auto-label images for use in training fine-tuned object detection models
Project-URL: Homepage, https://github.com/NourEldin-Osama/autodistill-yoloe
Project-URL: Repository, https://github.com/NourEldin-Osama/autodistill-yoloe
Author-email: NourEldin Osama <noureldin.osama.saad@gmail.com>
Classifier: Programming Language :: Python
Classifier: Programming Language :: Python :: 3
Classifier: Programming Language :: Python :: 3.11
Classifier: Programming Language :: Python :: 3.12
Classifier: Programming Language :: Python :: 3.13
Requires-Python: >=3.11
Requires-Dist: autodistill
Requires-Dist: pillow
Requires-Dist: roboflow
Requires-Dist: supervision
Requires-Dist: torch
Requires-Dist: ultralytics
